LICENSE
MANIFEST.in
ecs_composex_specs/__init__.py
ecs_composex_specs/compose-spec.json
ecs_composex_specs/ecs_composex_specs.py
ecs_composex_specs/ingress.spec.json
ecs_composex_specs/secrets.x-secrets.spec.json
ecs_composex_specs/services.x-alarms.spec.json
ecs_composex_specs/services.x-codeguru_profiler.spec.json
ecs_composex_specs/services.x-docker_opts.spec.json
ecs_composex_specs/services.x-ecr.spec.json
ecs_composex_specs/services.x-ecs.spec.json
ecs_composex_specs/services.x-iam.spec.json
ecs_composex_specs/services.x-logging.spec.json
ecs_composex_specs/services.x-network.spec.json
ecs_composex_specs/services.x-prometheus.spec.json
ecs_composex_specs/services.x-scaling.spec.json
ecs_composex_specs/x-acm.spec.json
ecs_composex_specs/x-alarms.spec.json
ecs_composex_specs/x-appmesh.spec.json
ecs_composex_specs/x-cluster.spec.json
ecs_composex_specs/x-cognito_userpool.spec.json
ecs_composex_specs/x-dashboards.spec.json
ecs_composex_specs/x-dns.spec.json
ecs_composex_specs/x-docdb.spec.json
ecs_composex_specs/x-dynamodb.spec.json
ecs_composex_specs/x-efs.spec.json
ecs_composex_specs/x-elbv2.spec.json
ecs_composex_specs/x-events.spec.json
ecs_composex_specs/x-kinesis.spec.json
ecs_composex_specs/x-kms.spec.json
ecs_composex_specs/x-rds.spec.json
ecs_composex_specs/x-resources.common.spec.json
ecs_composex_specs/x-s3.spec.json
ecs_composex_specs/x-sqs.spec.json
ecs_composex_specs/x-ssm_parameter.spec.json
ecs_composex_specs/x-tags.spec.json
ecs_composex_specs/x-vpc.spec.json
ecs_composex_specs-0.2.14.dist-info/LICENSE
ecs_composex_specs-0.2.14.dist-info/WHEEL
ecs_composex_specs-0.2.14.dist-info/METADATA
ecs_composex_specs-0.2.14.dist-info/RECORD
