Metadata-Version: 2.1
Name: ecs-composex-specs
Version: 0.2.14
Summary: JSON Schema Specifications for ECS Compose-X
License: MPL-2.0
Keywords: compose-x,aws,jsonschema
Author: John Preston
Author-email: john@compose-x.io
Requires-Python: >=3.7,<4.0
Classifier: Development Status :: 2 - Pre-Alpha
Classifier: Intended Audience :: Developers
Classifier: License :: OSI Approved
Classifier: Natural Language :: English
Classifier: Programming Language :: Python :: 3
Classifier: Programming Language :: Python :: 3.7
Classifier: Programming Language :: Python :: 3.8
Classifier: Programming Language :: Python :: 3.9
Requires-Dist: jsonschema (>=3.2.0,<4.0.0)
